geo_vallarisGIFT/__init__.py
geo_vallarisGIFT/perform.py
geo_vallarisGIFT-1.5.1.dist-info/LICENSE.txt
geo_vallarisGIFT-1.5.1.dist-info/METADATA
geo_vallarisGIFT-1.5.1.dist-info/WHEEL
geo_vallarisGIFT-1.5.1.dist-info/top_level.txt
geo_vallarisGIFT-1.5.1.dist-info/RECORD
