Metadata-Version: 2.1
Name: geo-vallarisGIFT
Version: 1.5.1
Summary: A package to processing Vallaris Maps
Home-page: https://v2k.vallarismaps.com
Author: Wanida Panup
Author-email: keerati.p@gistda.or.th
Classifier: Programming Language :: Python :: 3
Classifier: License :: OSI Approved :: MIT License
Classifier: Operating System :: OS Independent
Requires-Python: >=3.6
License-File: LICENSE.txt
Requires-Dist: jsonschema
Requires-Dist: ndjson
Requires-Dist: geojson
Requires-Dist: requests
Requires-Dist: geopandas
Requires-Dist: pandas
Requires-Dist: rtree
Requires-Dist: numpy
Requires-Dist: shapely
Requires-Dist: tqdm
Requires-Dist: python-dotenv
Requires-Dist: matplotlib
Requires-Dist: earthpy
Requires-Dist: uuid
